django_task_blocker/__init__.py
django_task_blocker/django_task_blocker.py
django_task_blocker-0.1.3.4.dist-info/LICENSE
django_task_blocker-0.1.3.4.dist-info/METADATA
django_task_blocker-0.1.3.4.dist-info/WHEEL
django_task_blocker-0.1.3.4.dist-info/RECORD
